eqben/__init__.py
eqben/eqben_acc.py
eqben/eqben_logger.py
eqben/eqben_utils.py
eqben-0.0.1.dist-info/METADATA
eqben-0.0.1.dist-info/WHEEL
eqben-0.0.1.dist-info/licenses/LICENSE
eqben-0.0.1.dist-info/RECORD
