Metadata-Version: 2.1
Name: eqben
Version: 0.0.1
Summary: eqben is a easy-to-use toolkit which unifies the evaluation of EqBen and some related datasets.
Project-URL: Homepage, https://github.com/Wangt-CN/EqBen
Author-email: Tan Wang <wangt97@hotmail.com>
License:    Apache License
License-File: LICENSE
Classifier: License :: OSI Approved :: MIT License
Classifier: Operating System :: OS Independent
Classifier: Programming Language :: Python :: 3
Requires-Python: >=3.7
Requires-Dist: numpy>=1.18.0
Requires-Dist: pillow>=8.0.0
Requires-Dist: torch>=1.6.0
